Metadata-Version: 2.4
Name: llama-index-readers-preprocess
Version: 0.4.1
Summary: llama-index readers preprocess integration
Author-email: Your Name <you@example.com>
Maintainer: preprocess
License-Expression: MIT
License-File: LICENSE
Keywords: chunk,chunking,documents,preprocess
Requires-Python: <4.0,>=3.9
Requires-Dist: llama-index-core<0.15,>=0.13.0
Requires-Dist: pypreprocess<2,>=1.4.3
